pyactp/actp.so
pyactp/__init__.py
pyactp/dummy.cpython-35m-i386-linux-gnu.so
pyactp-0.1.10.dist-info/WHEEL
pyactp-0.1.10.dist-info/top_level.txt
pyactp-0.1.10.dist-info/METADATA
pyactp-0.1.10.dist-info/RECORD
