Metadata-Version: 2.1
Name: pyactp
Version: 0.1.10
Summary: Python bindings for ACTP
Home-page: https://github.com/mikedh/pyactp
Author: Michael Dawson-Haggerty
Author-email: mik3dh@gmail.com
License: GPL
Keywords: actp milling toolpath
Platform: UNKNOWN
Classifier: Development Status :: 3 - Alpha
Classifier: License :: OSI Approved :: GNU General Public License v2 (GPLv2)
Classifier: Operating System :: POSIX :: Linux
Classifier: Programming Language :: Python :: 3.3
Classifier: Programming Language :: Python :: 3.4
Classifier: Programming Language :: Python :: 3.5
Classifier: Programming Language :: Python :: 3.6
